{
  "norm_file":"normNML_Gaussian_N1000d3K10.json",
  "simulation":{
    "iter":1
  },
  "clustering_params":{
    "num_em":10, "":"Number of times of EM algorithm",
    "max_clu":10, "":"Search range of the number of clusters"
  },
  "sdms_params":{
    "sdms_lam":30, "":"Scale of change code-length in SDMS",
    "sdms_beta":[2,30], "":"Parameters of prior distribution for change in SDMS (beta-distribution)"
  },
  "sim_params":{
    "temp_beta_unit":1, "":"The constant term of temperature beta",
    "th_change_diff":0.1, "":"The threshold to detect symptom with Diff",
    "th_change_th":0.1, "":"The threshold to detect symptom with TH",
    "th_change_sdms":0.5, "":"The threshold to detect symptom with SDMS",
    "th_change_fs":0.5, "":"The threshold to detect symptom with FS",
    "th_change_ws_fs":0.1, "":"The threshold to detect symptom with weighted average FS",
    "th_change_ws_fs_th":0.1, "":"The threshold to detect symptom with weighted average FS (threshold method)",
    "fs_alpha":0.2, "":"The weight parameter of fixed share algorithm",
    "fs_temp_beta":1.0, "":"The weight parameter of fixed share algorithm"
  }
}
